driveix/__init__.py
driveix/version.py
driveix/bpnet/__init__.py
driveix/bpnet/dataio/__init__.py
driveix/bpnet/dataio/build_converter.py
driveix/bpnet/dataio/coco_converter.py
driveix/bpnet/dataio/coco_dataset.py
driveix/bpnet/dataio/dataset_converter.py
driveix/bpnet/dataio/dataset_converter_lib.py
driveix/bpnet/dataloaders/__init__.py
driveix/bpnet/dataloaders/bpnet_dataloader.py
driveix/bpnet/dataloaders/dataset_config.py
driveix/bpnet/dataloaders/pose_config.py
driveix/bpnet/dataloaders/processors/__init__.py
driveix/bpnet/dataloaders/processors/augmentation.py
driveix/bpnet/dataloaders/processors/augmentation_utils.py
driveix/bpnet/dataloaders/processors/label_processor.py
driveix/bpnet/entrypoint/__init__.py
driveix/bpnet/entrypoint/bpnet.py
driveix/bpnet/exporter/__init__.py
driveix/bpnet/exporter/bpnet_exporter.py
driveix/bpnet/inferencer/__init__.py
driveix/bpnet/inferencer/bpnet_inferencer.py
driveix/bpnet/inferencer/postprocessor.py
driveix/bpnet/inferencer/utils.py
driveix/bpnet/learning_rate_schedules/__init__.py
driveix/bpnet/learning_rate_schedules/exponential_decay_schedule.py
driveix/bpnet/losses/__init__.py
driveix/bpnet/losses/bpnet_loss.py
driveix/bpnet/models/__init__.py
driveix/bpnet/models/bpnet_lite_model.py
driveix/bpnet/models/bpnet_model.py
driveix/bpnet/models/templates/__init__.py
driveix/bpnet/models/templates/helnet.py
driveix/bpnet/models/templates/utils.py
driveix/bpnet/models/templates/vgg.py
driveix/bpnet/optimizers/__init__.py
driveix/bpnet/optimizers/weighted_momentum_optimizer.py
driveix/bpnet/scripts/__init__.py
driveix/bpnet/scripts/dataset_convert.py
driveix/bpnet/scripts/evaluate.py
driveix/bpnet/scripts/export.py
driveix/bpnet/scripts/inference.py
driveix/bpnet/scripts/prune.py
driveix/bpnet/scripts/train.py
driveix/bpnet/trainers/__init__.py
driveix/bpnet/trainers/bpnet_trainer.py
driveix/bpnet/utils/__init__.py
driveix/bpnet/utils/dataio_utils.py
driveix/bpnet/utils/export_utils.py
driveix/bpnet/utils/model_utils.py
nvidia_tao_tf1-4.0.0.657.dev0.dist-info/LICENSE
nvidia_tao_tf1-4.0.0.657.dev0.dist-info/METADATA
nvidia_tao_tf1-4.0.0.657.dev0.dist-info/WHEEL
nvidia_tao_tf1-4.0.0.657.dev0.dist-info/entry_points.txt
nvidia_tao_tf1-4.0.0.657.dev0.dist-info/top_level.txt
nvidia_tao_tf1-4.0.0.657.dev0.dist-info/RECORD
