Metadata-Version: 2.1
Name: nvidia-tao-tf1
Version: 4.0.0.657.dev0
Summary: NVIDIA's Deep Learning Training SDK developed on TF1.x for TAO Toolkit.
Home-page: UNKNOWN
Author: NVIDIA Corporation
Author-email: UNKNOWN
License: NVIDIA Proprietary Software
Keywords: nvidia,tao toolkit,tensorflow
Platform: UNKNOWN
Classifier: Development Status :: 3 - Alpha
Classifier: Intended Audience :: Developers
Classifier: Topic :: Software Development :: Libraries
Classifier: Topic :: Software Development :: Libraries :: Python Modules
Classifier: Environment :: Console
Classifier: License :: Other/Proprietary License
Classifier: Programming Language :: Python :: 3
Classifier: Topic :: Scientific/Engineering :: Artificial Intelligence
